{
  "project_info": {
    "project_number": "431835019901",
    "project_id": "tablettegourmande-8c7c5",
    "storage_bucket": "tablettegourmande-8c7c5.firebasestorage.app"
  },
  "client": [
    {
      "client_info": {
        "mobilesdk_app_id": "1:431835019901:android:bc51f742fbb3d2cc88cf14",
        "android_client_info": {
          "package_name": "com.example.tablettegourmande"
        }
      },
      "oauth_client": [],
      "api_key": [
        {
          "current_key": "AIzaSyAEdCYEkDIiMEZ_YjPjsVGv9b3SqQTZiGA"
        }
      ],
      "services": {
        "appinvite_service": {
          "other_platform_oauth_client": []
        }
      }
    }
  ],
  "configuration_version": "1"
}